teuvo/__init__.py
teuvo/_modidx.py
teuvo/core.py
teuvo-0.0.2.dist-info/LICENSE
teuvo-0.0.2.dist-info/METADATA
teuvo-0.0.2.dist-info/WHEEL
teuvo-0.0.2.dist-info/entry_points.txt
teuvo-0.0.2.dist-info/top_level.txt
teuvo-0.0.2.dist-info/RECORD
